mcp_llms/__init__.py
mcp_llms/llms_txt.py
mseep_mcp_llms_txt-0.1.2.dist-info/METADATA
mseep_mcp_llms_txt-0.1.2.dist-info/WHEEL
mseep_mcp_llms_txt-0.1.2.dist-info/top_level.txt
mseep_mcp_llms_txt-0.1.2.dist-info/RECORD
